socksio/__init__.py
socksio/compat.py
socksio/exceptions.py
socksio/py.typed
socksio/socks4.py
socksio/socks5.py
socksio/utils.py
socksio-0.2.0.dist-info/LICENSE
socksio-0.2.0.dist-info/WHEEL
socksio-0.2.0.dist-info/METADATA
socksio-0.2.0.dist-info/RECORD
