Metadata-Version: 2.1
Name: socksio
Version: 0.2.0
Summary: Sans-I/O implementation of SOCKS4, SOCKS4A, and SOCKS5.
Home-page: https://github.com/sethmlarson/socksio
License: UNKNOWN
Author: Seth Michael Larson
Author-email: sethmichaellarson@gmail.com
Requires-Python: >=3.6
Classifier: License :: OSI Approved :: MIT License
Classifier: Programming Language :: Python :: 3.6
Classifier: Programming Language :: Python :: 3.7
Classifier: Programming Language :: Python :: 3.8
Classifier: Programming Language :: Python :: 3.9
Classifier: Programming Language :: Python :: 3 :: Only
Classifier: Topic :: Internet :: Proxy Servers
